knowledge_graph_maker/__init__.py
knowledge_graph_maker/graph_maker.py
knowledge_graph_maker/llm_clients/groq_client.py
knowledge_graph_maker/llm_clients/openai_client.py
knowledge_graph_maker/logger.py
knowledge_graph_maker/neo4j_graph_model.py
knowledge_graph_maker/types.py
knowledge_graph_maker-0.2.1.dist-info/LICENSE
knowledge_graph_maker-0.2.1.dist-info/METADATA
knowledge_graph_maker-0.2.1.dist-info/WHEEL
knowledge_graph_maker-0.2.1.dist-info/RECORD
