Metadata-Version: 2.1
Name: knowledge-graph-maker
Version: 0.2.1
Summary: Create knowledge graph out of any text using a given ontology
Author: Rahul Nayak
Author-email: rahul.nyk@gmail.com
Requires-Python: >=3.11,<4.0
Classifier: Programming Language :: Python :: 3
Classifier: Programming Language :: Python :: 3.11
Classifier: Programming Language :: Python :: 3.12
Requires-Dist: groq (>=0.6.0,<0.7.0)
Requires-Dist: jupyterlab (>=4.0.8,<5.0.0)
Requires-Dist: neo4j (==5.19.0)
Requires-Dist: neomodel (>=5.3.0,<6.0.0)
Requires-Dist: numpy (>=1.26.2,<2.0.0)
Requires-Dist: openai (>=1.28.0,<2.0.0)
Requires-Dist: pathlib (>=1.0.1,<2.0.0)
Requires-Dist: python-dotenv (>=1.0.1,<2.0.0)
Requires-Dist: uuid (>=1.30,<2.0)
Requires-Dist: yachalk (>=0.1.5,<0.2.0)
